[{"ID":"1\n","QTY":"5.0M\n","NO":"80A\n","DESCRIPTION":"PIPE SUS304TP SMLS BE SCH10S\n"},{"ID":"2\n","QTY":"12.6M\n","NO":"150A\n","DESCRIPTION":"PIPE SUS304TP SMLS BE SCH10S\n"},{"ID":"3\n","QTY":"3\n","NO":"80A\n","DESCRIPTION":"ELBOW SUS304TP BE SCH10S\n"},{"ID":"4\n","QTY":"1\n","NO":"450AX80A,\n","DESCRIPTION":"RED TEE SUS304TP BE SCH10S\n"},{"ID":"5\n","QTY":"1\n","NO":"80A\n","DESCRIPTION":"TEE SUS304TP BE SCH10S\n"},{"ID":"6\n","QTY":"4\n","NO":"80A\n","DESCRIPTION":"FLANGE KS 10K SO FF, KBS1503, STS304\n"},{"ID":"7\n","QTY":"1\n","NO":"80A\n","DESCRIPTION":"FLANGE KS 10K SO FF, KBS1503, STS304\n"},{"ID":"8\n","QTY":"20\n","NO":"M19X85L\n","DESCRIPTION":"STUD BOLT\/ NUT STS304B\n"},{"ID":"9\n","QTY":"5\n","NO":"80A\n","DESCRIPTION":"GASKET KS 10K 3048S SPW 4.5T\n"},{"ID":"10\n","QTY":"2\n","NO":"80A\n","DESCRIPTION":"BALL VALVE KS 10K RF, KSB2308, STS304\n"}]